source/dff_macros.sv
`ifndef DFF_MACROS_SV
`define DFF_MACROS_SV

`define DFF(Q, D, CLK, RST, RESET_VAL) \
    always_ff @(posedge CLK or posedge RST) begin \
        if (RST) Q <= RESET_VAL; \
        else     Q <= D; \
    end

`endif

traffic_light.sv
`include "dff_macros.sv"
// Traffic Light Controller
module traffic_light #(
    parameter int RED_T     = 20,
    parameter int REDYLW_T = 4,
    parameter int GREEN_T   = 20,
    parameter int YELLOW_T  = 4
)(
    input  logic clk,
    input  logic rst,
    output logic red,
    output logic yellow,
    output logic green
);

    // State encoding using localparam
    localparam logic [1:0] S_RED    = 2'd0;
    localparam logic [1:0] S_REDYLW = 2'd1;
    localparam logic [1:0] S_GREEN  = 2'd2;
    localparam logic [1:0] S_YELLOW = 2'd3;

    logic [1:0] state, next_state;
    logic [4:0] timer, next_timer;

    // Instantiate flip-flops using dff macro
    `DFF(state, next_state, clk, rst, S_RED)
    `DFF(timer, next_timer, clk, rst, RED_T-1)

    // Next-state logic
    always_comb begin
        case (state)
            S_RED:     next_state = (timer == 0) ? S_REDYLW : S_RED;
            S_REDYLW:  next_state = (timer == 0) ? S_GREEN  : S_REDYLW;
            S_GREEN:   next_state = (timer == 0) ? S_YELLOW : S_GREEN;
            S_YELLOW:  next_state = (timer == 0) ? S_RED    : S_YELLOW;
            default:   next_state = S_RED;
        endcase
    end

    // Timer logic
    always_comb begin
        if (rst) begin
            next_timer = RED_T-1;
        end else if (timer > 0) begin
            next_timer = timer - 1;
        end else begin
            case (state)
                S_RED:     next_timer = REDYLW_T - 1;
                S_REDYLW:  next_timer = GREEN_T  - 1;
                S_GREEN:   next_timer = YELLOW_T - 1;
                S_YELLOW:  next_timer = RED_T    - 1;
                default:   next_timer = RED_T    - 1;
            endcase
        end
    end

    // Output logic
    always_comb begin
        red    = (state == S_RED || state == S_REDYLW);
        yellow = (state == S_REDYLW || state == S_YELLOW);
        green  = (state == S_GREEN);
    end

endmodule

tb_traffic_light.sv
// tb_traffic_light.sv - Testbench for traffic_light.sv using the same macro-driven style
`timescale 1ns / 1ps

module tb_traffic_light;

    logic clk = 0;
    logic rst = 1;
    logic red, yellow, green;

    // Clock generator
    always #5 clk = ~clk; // 10ns clock period (100 MHz)

    // Instantiate the DUT
    traffic_light #(
        .RED_T(6),
        .REDYLW_T(2),
        .GREEN_T(6),
        .YELLOW_T(2)
    ) dut (
        .clk(clk),
        .rst(rst),
        .red(red),
        .yellow(yellow),
        .green(green)
    );

    initial begin
        // Dump waveform
        $dumpfile("traffic.vcd");
        $dumpvars(0, tb_traffic_light);

        // Hold reset
        #20 rst = 0;

        // Run simulation for some time
        #200;
        $finish;
    end

endmodule

build/traffic.vcd
$date
	Tue May  6 00:49:01 2025
$end
$version
	Icarus Verilog
$end
$timescale
	1ps
$end
$scope module tb_traffic_light $end
$var wire 1 ! yellow $end
$var wire 1 " red $end
$var wire 1 # green $end
$var reg 1 $ clk $end
$var reg 1 % rst $end
$scope module dut $end
$var wire 1 $ clk $end
$var wire 1 % rst $end
$var parameter 32 & GREEN_T $end
$var parameter 32 ' REDYLW_T $end
$var parameter 32 ( RED_T $end
$var parameter 2 ) S_GREEN $end
$var parameter 2 * S_RED $end
$var parameter 2 + S_REDYLW $end
$var parameter 2 , S_YELLOW $end
$var parameter 32 - YELLOW_T $end
$var reg 1 # green $end
$var reg 2 . next_state [1:0] $end
$var reg 5 / next_timer [4:0] $end
$var reg 1 " red $end
$var reg 2 0 state [1:0] $end
$var reg 5 1 timer [4:0] $end
$var reg 1 ! yellow $end
$upscope $end
$upscope $end
$enddefinitions $end
$comment Show the parameter values. $end
$dumpall
b10 -
b11 ,
b1 +
b0 *
b10 )
b110 (
b10 '
b110 &
$end
#0
$dumpvars
bx 1
bx 0
b101 /
b0 .
1%
0$
x#
x"
x!
$end
#5000
0#
0!
1"
b0 0
b101 1
1$
#10000
0$
#15000
1$
#20000
b100 /
0$
0%
#25000
b11 /
b100 1
1$
#30000
0$
#35000
b10 /
b11 1
1$
#40000
0$
#45000
b1 /
b10 1
1$
#50000
0$
#55000
b0 /
b1 1
1$
#60000
0$
#65000
b1 /
b1 .
b0 1
1$
#70000
0$
#75000
1!
b0 /
b1 1
b1 0
1$
#80000
0$
#85000
b101 /
b10 .
b0 1
1$
#90000
0$
#95000
1#
0!
0"
b100 /
b101 1
b10 0
1$
#100000
0$
#105000
b11 /
b100 1
1$
#110000
0$
#115000
b10 /
b11 1
1$
#120000
0$
#125000
b1 /
b10 1
1$
#130000
0$
#135000
b0 /
b1 1
1$
#140000
0$
#145000
b1 /
b11 .
b0 1
1$
#150000
0$
#155000
0#
1!
b0 /
b1 1
b11 0
1$
#160000
0$
#165000
b101 /
b0 .
b0 1
1$
#170000
0$
#175000
0!
1"
b100 /
b101 1
b0 0
1$
#180000
0$
#185000
b11 /
b100 1
1$
#190000
0$
#195000
b10 /
b11 1
1$
#200000
0$
#205000
b1 /
b10 1
1$
#210000
0$
#215000
b0 /
b1 1
1$
